shell_lib/__init__.py
shell_lib/py.typed
shell_lib/shell_lib.py
shell_lib/powershell/__init__.py
shell_lib-2.0.2.dist-info/METADATA
shell_lib-2.0.2.dist-info/WHEEL
shell_lib-2.0.2.dist-info/top_level.txt
shell_lib-2.0.2.dist-info/RECORD
