Metadata-Version: 2.4
Name: shell-lib
Version: 2.0.2
Summary: A Python utility to simplify the writing of shell-like scripts.
Author-email: Ma Lin <malincns@163.com>, Google Gemini <no@no.com>
License-Expression: MIT
Project-URL: Repository, https://bitbucket.org/wjssz/shell_lib
Project-URL: Documentation, https://shell-lib.readthedocs.io
Project-URL: Changelog, https://shell-lib.readthedocs.io/changelog.html
Classifier: Programming Language :: Python :: 3
Classifier: Development Status :: 4 - Beta
Classifier: Topic :: System :: Shells
Classifier: Topic :: Utilities
Classifier: Operating System :: Unix
Classifier: Operating System :: POSIX
Classifier: Operating System :: MacOS
Classifier: Operating System :: Microsoft :: Windows
Requires-Python: >=3.7
